pythonoscquery/__init__.py
pythonoscquery/osc_query_browser.py
pythonoscquery/osc_query_client.py
pythonoscquery/osc_query_service.py
pythonoscquery/py.typed
pythonoscquery/pythonosc_callback_wrapper.py
pythonoscquery/shared/__init__.py
pythonoscquery/shared/osc_access.py
pythonoscquery/shared/osc_address_space.py
pythonoscquery/shared/osc_host_info.py
pythonoscquery/shared/osc_path_node.py
pythonoscquery/shared/osc_spec.py
pythonoscquery/shared/oscquery_spec.py
python_oscquery-0.3.0.dist-info/licenses/LICENSE
python_oscquery-0.3.0.dist-info/WHEEL
python_oscquery-0.3.0.dist-info/METADATA
python_oscquery-0.3.0.dist-info/RECORD
