Metadata-Version: 2.4
Name: python-oscquery
Version: 0.3.0
Summary: OSCQuery library to advertise an Open Sound Control (OSC) service
Keywords: osc,sound,midi,music,audio,lighting,video,show control
Author: Cyberkitsune, Frank Klein
Author-email: Frank Klein <4243101+fraklein@users.noreply.github.com>
License-Expression: MIT
License-File: LICENSE
Classifier: Development Status :: 4 - Beta
Classifier: Intended Audience :: Developers
Classifier: Topic :: Software Development :: Build Tools
Classifier: Programming Language :: Python :: 3
Classifier: Programming Language :: Python :: 3.10
Classifier: Programming Language :: Python :: 3.11
Classifier: Programming Language :: Python :: 3.12
Classifier: Programming Language :: Python :: 3.13
Classifier: Programming Language :: Python :: 3.14
Classifier: License :: OSI Approved :: MIT License
Classifier: Topic :: Multimedia :: Sound/Audio
Classifier: Topic :: System :: Networking
Requires-Dist: python-osc>=1.9.3
Requires-Dist: requests>=2.32.5
Requires-Dist: zeroconf>=0.39.1
Requires-Python: >=3.10
Project-URL: Repository, https://github.com/fraklein/python-oscquery
